rasplinkgen/__init__.py
rasplinkgen/rasptube.py
rasptube-1.0.2.dist-info/LICENSE.txt
rasptube-1.0.2.dist-info/METADATA
rasptube-1.0.2.dist-info/WHEEL
rasptube-1.0.2.dist-info/top_level.txt
rasptube-1.0.2.dist-info/RECORD
